rapidminer_go_python/__init__.py
rapidminer_go_python/rapidminergoclient.py
rapidminer_go_python-0.0.6.dist-info/LICENSE
rapidminer_go_python-0.0.6.dist-info/METADATA
rapidminer_go_python-0.0.6.dist-info/WHEEL
rapidminer_go_python-0.0.6.dist-info/top_level.txt
rapidminer_go_python-0.0.6.dist-info/RECORD
