Metadata-Version: 2.1
Name: rapidminer-go-python
Version: 0.0.6
Summary: A python package to interact with RapidMiner GO Engine
Home-page: https://github.com/rapidminer-labs/python-go
Author: RapidMiner-Labs
Author-email: bpatil@rapidminer.com
License: UNKNOWN
Platform: UNKNOWN
Classifier: Programming Language :: Python :: 3
Classifier: License :: OSI Approved :: MIT License
Classifier: Operating System :: OS Independent
Requires-Python: >=3.6
Requires-Dist: tabpy
Requires-Dist: matplotlib (==3.1)
Requires-Dist: tabpy-client
